silver_surfer_models/__init__.py
silver_surfer_models/database/__init__.py
silver_surfer_models/resources/__init__.py
silver_surfer_models/resources/all_models.py
silver_surfer_models/resources/AbstractText/__init__.py
silver_surfer_models/resources/AbstractText/models.py
silver_surfer_models/resources/AbstractText/schemas.py
silver_surfer_models/resources/AbstractText/test_abstract_text.py
silver_surfer_models/resources/Claim/__init__.py
silver_surfer_models/resources/Claim/models.py
silver_surfer_models/resources/Claim/schemas.py
silver_surfer_models/resources/Claim/test_claim.py
silver_surfer_models/resources/ClaimChallenged/__init__.py
silver_surfer_models/resources/ClaimChallenged/models.py
silver_surfer_models/resources/ClaimChallenged/schemas.py
silver_surfer_models/resources/ClaimChallenged/test_claim_challenged.py
silver_surfer_models/resources/ClaimDependency/__init__.py
silver_surfer_models/resources/ClaimDependency/models.py
silver_surfer_models/resources/ClaimDependency/schemas.py
silver_surfer_models/resources/ClaimDependency/test_claim_dependency.py
silver_surfer_models/resources/Company/__init__.py
silver_surfer_models/resources/Company/models.py
silver_surfer_models/resources/Company/schemas.py
silver_surfer_models/resources/Company/test_company.py
silver_surfer_models/resources/CrossRef/__init__.py
silver_surfer_models/resources/CrossRef/models.py
silver_surfer_models/resources/CrossRef/schemas.py
silver_surfer_models/resources/CrossRef/test_crossref.py
silver_surfer_models/resources/DocumentReference/__init__.py
silver_surfer_models/resources/DocumentReference/models.py
silver_surfer_models/resources/DocumentReference/schemas.py
silver_surfer_models/resources/DocumentReference/test_document_reference.py
silver_surfer_models/resources/File/__init__.py
silver_surfer_models/resources/File/models.py
silver_surfer_models/resources/File/schemas.py
silver_surfer_models/resources/File/test_file.py
silver_surfer_models-0.0.56.dev0.dist-info/METADATA
silver_surfer_models-0.0.56.dev0.dist-info/WHEEL
silver_surfer_models-0.0.56.dev0.dist-info/top_level.txt
silver_surfer_models-0.0.56.dev0.dist-info/RECORD
